decoders/__init__.py
decoders/binary_transformer.py
decoders/fake_transformer.py
decoders/generation_mixin.py
decoders/small_prob_transformer.py
decoders/toolbox.py
decoders/simple/ancestral.py
decoders/simple/beam_search.py
decoders/simple/simple_beam_utils.py
decoders/simple/stochastic_beam_search.py
decoders/strategies/assisted_decoder.py
decoders/strategies/beam_constrained_decoder.py
decoders/strategies/beam_decoder.py
decoders/strategies/beam_utils.py
decoders/strategies/contrastive_decoder.py
decoders/strategies/diverse_group_beam_decoder.py
decoders/strategies/sampling_decoder.py
decoders/strategies/stochastic_beam_search.py
decoders/strategies/utils.py
decoders/strategies/sbs_helpers/gumbel.py
decoders/strategies/sbs_helpers/logits_process.py
decoders-0.4.0.dist-info/METADATA
decoders-0.4.0.dist-info/WHEEL
decoders-0.4.0.dist-info/licenses/LICENSE
decoders-0.4.0.dist-info/RECORD
