Metadata-Version: 2.4
Name: decoders
Version: 0.4.0
Summary: Diverse and extensible generation decoding libraries for transformers.
Project-URL: Homepage, https://github.com/manueldeprada/decoders
Project-URL: Change log, https://github.com/manueldeprada/decoders/blob/master/CHANGELOG.md
Author-email: Manuel de Prada Corral <manueldeprada@gmail.com>
License-File: LICENSE
Classifier: License :: OSI Approved :: Apache Software License
Classifier: Operating System :: OS Independent
Classifier: Programming Language :: Python :: 3
Requires-Python: >=3.9
Requires-Dist: transformers>=4.36.2
